COPYING
MANIFEST.in
NEWS.rst
README.rst
setup.py
byov/__init__.py
byov/commands.py
byov/config.py
byov/errors.py
byov/logs.py
byov/monitors.py
byov/options.py
byov/ssh.py
byov/subprocesses.py
byov/timeouts.py
byov/user_data.py
byov.egg-info/PKG-INFO
byov.egg-info/SOURCES.txt
byov.egg-info/dependency_links.txt
byov.egg-info/entry_points.txt
byov.egg-info/requires.txt
byov.egg-info/top_level.txt
byov/scripts/__init__.py
byov/scripts/bootstrap-scaleway-image
byov/scripts/create-glance-images
byov/scripts/create-lxd-amazon-image
byov/scripts/create-lxd-debian-image
byov/scripts/fix-locale
byov/scripts/get-lxd-cloud-images
byov/scripts/get-nova-cloud-images
byov/scripts/get-qemu-cloud-images
byov/scripts/get-qemu-debian-cloud-images
byov/scripts/no-random-upgrades
byov/scripts/stop-snap
byov/scripts/transform-scaleway-image
byov/scripts/unminimize-ubuntu
byov/scripts/first_use/byov
byov/scripts/first_use/install-lxd
byov/scripts/first_use/lxd
byov/scripts/first_use/qemu
byov/scripts/first_use/uninstall-lxd
byov/tests/__init__.py
byov/tests/features.py
byov/tests/fixtures.py
byov/tests/test_commands.py
byov/tests/test_config.py
byov/tests/test_docker.py
byov/tests/test_ec2.py
byov/tests/test_fixtures.py
byov/tests/test_logs.py
byov/tests/test_lxd.py
byov/tests/test_monitors.py
byov/tests/test_nova.py
byov/tests/test_pull.py
byov/tests/test_push.py
byov/tests/test_qemu.py
byov/tests/test_scaleway.py
byov/tests/test_setup_hook.py
byov/tests/test_setup_scripts.py
byov/tests/test_ssh.py
byov/tests/test_start_hook.py
byov/tests/test_styles.py
byov/tests/test_subprocesses.py
byov/tests/test_timeouts.py
byov/tests/test_user_data.py
byov/tests/test_vms.py
byov/vms/__init__.py
byov/vms/docker.py
byov/vms/ec2.py
byov/vms/lxd.py
byov/vms/nova.py
byov/vms/qemu.py
byov/vms/scaleway.py
byov/vms/ssh.py