Metadata-Version: 2.2
Name: byov
Version: 2.4.1
Summary: Build Your Own Virtual machine.
Home-page: https://launchpad.net/byov
Author: Vincent Ladeuil
Author-email: v.ladeuil+lp@free.fr
License: GPLv3
License-File: COPYING
Requires-Dist: python3-byoc
Requires-Dist: pexpect
Dynamic: author
Dynamic: author-email
Dynamic: description
Dynamic: home-page
Dynamic: license
Dynamic: requires-dist
Dynamic: summary
